lesscode/__init__.py
lesscode/config/__init__.py
lesscode/config/settings.py
lesscode/core/__init__.py
lesscode/core/cache.py
lesscode/core/database.py
lesscode/core/exception_handlers.py
lesscode/core/exceptions.py
lesscode/core/logging.py
lesscode/core/router.py
lesscode/core/status_codes.py
lesscode/models/__init__.py
lesscode/models/base.py
lesscode/repositories/__init__.py
lesscode/repositories/base.py
lesscode/schemas/__init__.py
lesscode/schemas/response.py
lesscode/server/__init__.py
lesscode/server/app.py
lesscode/server/run.py
lesscode/tools/__init__.py
lesscode/tools/fix_pylint.py
lesscode/utils/__init__.py
lesscode/utils/response.py
lesscode_fastapi-0.0.8.dist-info/METADATA
lesscode_fastapi-0.0.8.dist-info/WHEEL
lesscode_fastapi-0.0.8.dist-info/entry_points.txt
lesscode_fastapi-0.0.8.dist-info/top_level.txt
lesscode_fastapi-0.0.8.dist-info/RECORD
