Metadata-Version: 2.4
Name: lesscode-fastapi
Version: 0.0.8
Summary: lesscode-fastapi 是基于FastAPI的web开发脚手架项目，该项目初衷为简化开发过程，让研发人员更加关注业务。
Home-page: https://lesscode-fastapi
Author: Chao.yy
Author-email: yuyc@shangqi.com.cn
Platform: any
Classifier: Programming Language :: Python :: 3
Classifier: Operating System :: OS Independent
Requires-Python: >=3.9
Requires-Dist: fastapi==0.116.1
Requires-Dist: starlette==0.47.3
Requires-Dist: uvicorn[standard]==0.35.0
Requires-Dist: pydantic-settings==2.10.1
Requires-Dist: loguru==0.7.3
Requires-Dist: sqlalchemy==2.0.43
Requires-Dist: redis==6.4.0
Requires-Dist: pydantic==2.11.7
Requires-Dist: pyyaml==6.0.2
Dynamic: author
Dynamic: author-email
Dynamic: classifier
Dynamic: description
Dynamic: description-content-type
Dynamic: home-page
Dynamic: platform
Dynamic: requires-dist
Dynamic: requires-python
Dynamic: summary
